evolutiongaming/__init__.py
evolutiongaming/downloader.py
evolutiongaming_bundle_downloader-1.1.dist-info/METADATA
evolutiongaming_bundle_downloader-1.1.dist-info/WHEEL
evolutiongaming_bundle_downloader-1.1.dist-info/top_level.txt
evolutiongaming_bundle_downloader-1.1.dist-info/RECORD
