Metadata-Version: 2.1
Name: evolutiongaming-bundle-downloader
Version: 1.1
Summary: Downloads all available games from the bundle repository.
Home-page: https://bundle-repo.evo-games.com
Author: Ozgur Vatansever
Author-email: ozgurvt@gmail.com
License: UNKNOWN
Platform: UNKNOWN
Classifier: Programming Language :: Python :: 2.7
Classifier: License :: OSI Approved :: MIT License
Classifier: Operating System :: OS Independent
Requires-Python: >=2.7
Requires-Dist: requests
